cylinder.py
cylinder-0.0.6.dist-info/LICENSE
cylinder-0.0.6.dist-info/METADATA
cylinder-0.0.6.dist-info/WHEEL
cylinder-0.0.6.dist-info/top_level.txt
cylinder-0.0.6.dist-info/RECORD
